foocheck/__init__.py
foocheck/cli.py
foocheck/networks.py
foocheck/sites.py
foocheck/utils.py
foocheck-0.5.0.dist-info/LICENSE
foocheck-0.5.0.dist-info/METADATA
foocheck-0.5.0.dist-info/WHEEL
foocheck-0.5.0.dist-info/entry_points.txt
foocheck-0.5.0.dist-info/RECORD
