Metadata-Version: 2.3
Name: foocheck
Version: 0.5.0
Summary: A username checker
Author: walidsa3d
Requires-Python: >=3.10,<4.0
Classifier: Programming Language :: Python :: 3
Classifier: Programming Language :: Python :: 3.10
Classifier: Programming Language :: Python :: 3.11
Classifier: Programming Language :: Python :: 3.12
Classifier: Programming Language :: Python :: 3.13
Requires-Dist: click (>=8.1.3,<9.0.0)
Requires-Dist: httpx[http2] (>=0.28.1,<0.29.0)
Requires-Dist: sphinx-autodoc-typehints (>=3.0.0,<4.0.0)
